{
  "title": "SSC CHSL 2020 Part 1 Antonyms",
  "slug": "ssc-chsl-2020-part-1-antonyms",
  "questions": [
    {
      "question": "RESOLVE",
      "option_1": "agree",
      "option_2": "analyse",
      "option_3": "refuse",
      "option_4": "decide",
      "answer": "3",
      "solution": ""
    },
    {
      "question": "PRECIOUS",
      "option_1": "rare",
      "option_2": "costly",
      "option_3": "cheap",
      "option_4": "simple",
      "answer": "3",
      "solution": ""
    },
    {
      "question": "AUGMENT",
      "option_1": "amplify",
      "option_2": "multiply",
      "option_3": "increase",
      "option_4": "decrease",
      "answer": "4",
      "solution": ""
    },
    {
      "question": "VITIATE",
      "option_1": "Affirm",
      "option_2": "Annul",
      "option_3": "Cancel",
      "option_4": "Violate",
      "answer": "1",
      "solution": ""
    },
    {
      "question": "Bias",
      "option_1": "Stage",
      "option_2": "Prejudice",
      "option_3": "Fairness",
      "option_4": "Prestige",
      "answer": "3",
      "solution": ""
    },
    {
      "question": "Fritter",
      "option_1": "Spread",
      "option_2": "Spoil",
      "option_3": "Hoard",
      "option_4": "Waste",
      "answer": "3",
      "solution": ""
    },
    {
      "question": "FRIGID",
      "option_1": "Salty",
      "option_2": "Warm",
      "option_3": "Chilly",
      "option_4": "Frosty",
      "answer": "2",
      "solution": ""
    },
    {
      "question": "STRETCH",
      "option_1": "Lengthen",
      "option_2": "Extend",
      "option_3": "Compress",
      "option_4": "Elongate",
      "answer": "3",
      "solution": ""
    },
    {
      "question": "INNOCUOUS",
      "option_1": "indifferent",
      "option_2": "innocent",
      "option_3": "harmful",
      "option_4": "harmless",
      "answer": "3",
      "solution": ""
    },
    {
      "question": "SEVERE",
      "option_1": "Harsh",
      "option_2": "Mild",
      "option_3": "Strict",
      "option_4": "Cruel",
      "answer": "2",
      "solution": ""
    },
    {
      "question": "CORROBORATE",
      "option_1": "confirm",
      "option_2": "validate",
      "option_3": "verify",
      "option_4": "oppose",
      "answer": "4",
      "solution": ""
    },
    {
      "question": "Intrepid",
      "option_1": "Responsive",
      "option_2": "Cowardly",
      "option_3": "Sentimental",
      "option_4": "Unemotional",
      "answer": "2",
      "solution": ""
    },
    {
      "question": "TRANSPARENT",
      "option_1": "shining",
      "option_2": "clean",
      "option_3": "opaque",
      "option_4": "beautiful",
      "answer": "3",
      "solution": ""
    },
    {
      "question": "BLUNT",
      "option_1": "dull",
      "option_2": "pointless",
      "option_3": "sharp",
      "option_4": "round",
      "answer": "3",
      "solution": ""
    },
    {
      "question": "MEAGRE",
      "option_1": "sufficient",
      "option_2": "scanty",
      "option_3": "scares",
      "option_4": "deficient",
      "answer": "1",
      "solution": ""
    },
    {
      "question": "HORRENDOUS",
      "option_1": "dreary",
      "option_2": "frightening",
      "option_3": "watchful",
      "option_4": "pleasant",
      "answer": "4",
      "solution": ""
    },
    {
      "question": "Transparent",
      "option_1": "Superficial",
      "option_2": "Shy",
      "option_3": "Clear",
      "option_4": "Opaque",
      "answer": "4",
      "solution": ""
    },
    {
      "question": "CONTAMINATE",
      "option_1": "pollute",
      "option_2": "cleanse",
      "option_3": "disturb",
      "option_4": "convert",
      "answer": "2",
      "solution": ""
    },
    {
      "question": "INORDINATE",
      "option_1": "disproportionate",
      "option_2": "exorbitant",
      "option_3": "reasonable",
      "option_4": "irrational",
      "answer": "3",
      "solution": ""
    },
    {
      "question": "PUNGENT",
      "option_1": "sharp",
      "option_2": "mild",
      "option_3": "biting",
      "option_4": "sour",
      "answer": "2",
      "solution": ""
    },
    {
      "question": "Bland",
      "option_1": "Weak",
      "option_2": "Exciting",
      "option_3": "Flimsy",
      "option_4": "Boring",
      "answer": "2",
      "solution": ""
    },
    {
      "question": "Pernicious",
      "option_1": "Malicious",
      "option_2": "Malcontent",
      "option_3": "Nefarious",
      "option_4": "Beneficial",
      "answer": "4",
      "solution": ""
    },
    {
      "question": "Hazy",
      "option_1": "Soft",
      "option_2": "Dim",
      "option_3": "Clear",
      "option_4": "Faint",
      "answer": "3",
      "solution": ""
    },
    {
      "question": "SPURIOUS",
      "option_1": "genuine",
      "option_2": "counterfeit",
      "option_3": "artificial",
      "option_4": "phony",
      "answer": "1",
      "solution": ""
    },
    {
      "question": "Resign",
      "option_1": "Reject",
      "option_2": "Join",
      "option_3": "Accept",
      "option_4": "Sign",
      "answer": "2",
      "solution": ""
    },
    {
      "question": "Malicious",
      "option_1": "Biased",
      "option_2": "Perverted",
      "option_3": "Culpable",
      "option_4": "Decent",
      "answer": "4",
      "solution": ""
    },
    {
      "question": "HASTE",
      "option_1": "drive",
      "option_2": "urgency",
      "option_3": "delay",
      "option_4": "pace",
      "answer": "3",
      "solution": ""
    },
    {
      "question": "PLUNGE",
      "option_1": "fall",
      "option_2": "dive",
      "option_3": "rise",
      "option_4": "duck",
      "answer": "3",
      "solution": ""
    },
    {
      "question": "GRACEFUL",
      "option_1": "pretty",
      "option_2": "awkward",
      "option_3": "dangerous",
      "option_4": "attractive",
      "answer": "2",
      "solution": ""
    },
    {
      "question": "Constant",
      "option_1": "Unchanging",
      "option_2": "Static",
      "option_3": "Competent",
      "option_4": "Fluctuating",
      "answer": "4",
      "solution": ""
    },
    {
      "question": "DEVIOUS",
      "option_1": "calculating",
      "option_2": "shrewd",
      "option_3": "Deceitful",
      "option_4": "straight",
      "answer": "4",
      "solution": ""
    },
    {
      "question": "SUSTENANCE",
      "option_1": "livelihood",
      "option_2": "starvation",
      "option_3": "refreshment",
      "option_4": "nourishment",
      "answer": "2",
      "solution": ""
    },
    {
      "question": "WISDOM",
      "option_1": "youth",
      "option_2": "stupidity",
      "option_3": "maturity",
      "option_4": "stability",
      "answer": "2",
      "solution": ""
    },
    {
      "question": "Weird",
      "option_1": "Abnormal",
      "option_2": "Normal",
      "option_3": "Wide",
      "option_4": "Apparent",
      "answer": "2",
      "solution": ""
    },
    {
      "question": "Harrowing",
      "option_1": "Pleasant",
      "option_2": "Stressful",
      "option_3": "Repetitive",
      "option_4": "Worrying",
      "answer": "1",
      "solution": ""
    },
    {
      "question": "INDIGNANT",
      "option_1": "Peeved",
      "option_2": "Annoyed",
      "option_3": "Upset",
      "option_4": "Pleased",
      "answer": "4",
      "solution": ""
    },
    {
      "question": "Disheveled",
      "option_1": "Untidy",
      "option_2": "Unkempt",
      "option_3": "Cluttered",
      "option_4": "Ordered",
      "answer": "4",
      "solution": ""
    },
    {
      "question": "Accustomed",
      "option_1": "Ordinary",
      "option_2": "Terrific",
      "option_3": "Unusual",
      "option_4": "Fabulous",
      "answer": "3",
      "solution": ""
    },
    {
      "question": "Compel",
      "option_1": "Influence",
      "option_2": "Persuade",
      "option_3": "Dissuade",
      "option_4": "Induce",
      "answer": "3",
      "solution": ""
    },
    {
      "question": "Naïve",
      "option_1": "Unsuspicious",
      "option_2": "Immature",
      "option_3": "Simple",
      "option_4": "Sophisticated",
      "answer": "4",
      "solution": ""
    }
  ]
}